ro/__init__.py
ro/core/__init__.py
ro/core/base.py
ro/core/exceptions.py
ro/core/meta.py
ro/core/signals.py
ro/core/utils.py
ro/orm/__init__.py
ro/orm/orm.py
ro/orm/signals.py
ro/orm/sqlite_.py
ro/orm/utils.py
raccy_orm-0.0.1.dist-info/LICENSE
raccy_orm-0.0.1.dist-info/METADATA
raccy_orm-0.0.1.dist-info/WHEEL
raccy_orm-0.0.1.dist-info/top_level.txt
raccy_orm-0.0.1.dist-info/RECORD
